literotica_dl2/__about__.py
literotica_dl2/__init__.py
literotica_dl2/__main__.py
literotica_dl2/author.py
literotica_dl2/cli.py
literotica_dl2/literotica_dl2.py
literotica_dl2/poem.py
literotica_dl2/story.py
literotica_dl2/story_series.py
literotica_dl2/utils.py
literotica_dl2-0.1.2.dist-info/METADATA
literotica_dl2-0.1.2.dist-info/WHEEL
literotica_dl2-0.1.2.dist-info/entry_points.txt
literotica_dl2-0.1.2.dist-info/licenses/LICENSE.txt
literotica_dl2-0.1.2.dist-info/RECORD
