Metadata-Version: 2.4
Name: literotica-dl2
Version: 0.1.2
Summary: A tool to download stories from Literotica
Project-URL: Documentation, https://github.com/ShamoliShah/literotica-dl2#readme
Project-URL: Issues, https://github.com/ShamoliShah/literotica-dl2/issues
Project-URL: Source, https://github.com/ShamoliShah/literotica-dl2
Author-email: Shamoli Shah <64245803+shamolishah@users.noreply.github.com>
License-Expression: MIT
License-File: LICENSE.txt
Classifier: Development Status :: 4 - Beta
Classifier: Programming Language :: Python
Classifier: Programming Language :: Python :: 3.8
Classifier: Programming Language :: Python :: 3.9
Classifier: Programming Language :: Python :: 3.10
Classifier: Programming Language :: Python :: 3.11
Classifier: Programming Language :: Python :: 3.12
Classifier: Programming Language :: Python :: Implementation :: CPython
Classifier: Programming Language :: Python :: Implementation :: PyPy
Requires-Python: >=3.8
Requires-Dist: beautifulsoup4
Requires-Dist: fake-useragent
Requires-Dist: html5lib
Requires-Dist: markdownify
Requires-Dist: requests
Requires-Dist: requests-cache
Requires-Dist: typer
